dessert/__init__.py
dessert/__version__.py
dessert/conf.py
dessert/pathlib.py
dessert/rewrite.py
dessert/saferepr.py
dessert/util.py
dessert/warning_types.py
dessert-1.5.0.dist-info/METADATA
dessert-1.5.0.dist-info/WHEEL
dessert-1.5.0.dist-info/licenses/LICENSE
dessert-1.5.0.dist-info/RECORD
