Metadata-Version: 2.3
Name: dessert
Version: 1.5.0
Summary: Assertion introspection via AST rewriting
Project-URL: GitHub, https://github.com/vmalloc/dessert
Author-email: Rotem Yaari <vmalloc@gmail.com>
License: MIT
License-File: LICENSE
Classifier: Programming Language :: Python :: 3.8
Classifier: Programming Language :: Python :: 3.9
Classifier: Programming Language :: Python :: 3.10
Classifier: Programming Language :: Python :: 3.11
Classifier: Programming Language :: Python :: 3.12
Classifier: Programming Language :: Python :: 3.13
Requires-Python: >=3.8
Requires-Dist: atomicwrites>=1.0
Requires-Dist: attrs
Requires-Dist: munch
Requires-Dist: py
Provides-Extra: testing
Requires-Dist: emport>=1.1.1; extra == 'testing'
Requires-Dist: pylint; extra == 'testing'
Requires-Dist: pytest; extra == 'testing'
